{
    "1": {
        "target_rect": [
            0,
            297
        ]
    },
    "2": {
        "target_rect": [
            0,
            258
        ]
    },
    "3": {
        "target_rect": [
            0,
            335
        ]
    },
    "4": {
        "target_rect": [
            0,
            165
        ]
    },
    "5": {
        "target_rect": [
            0,
            209
        ]
    },
    "6": {
        "target_rect": [
            0,
            308
        ]
    },
    "7": {
        "target_rect": [
            0,
            237
        ]
    },
    "8": {
        "target_rect": [
            0,
            275
        ]
    },
    "9": {
        "target_rect": [
            0,
            233
        ]
    },
    "10": {
        "target_rect": [
            0,
            227
        ]
    },
    "11": {
        "target_rect": [
            0,
            164
        ]
    },
    "12": {
        "target_rect": [
            0,
            308
        ]
    },
    "13": {
        "target_rect": [
            0,
            243
        ]
    },
    "14": {
        "target_rect": [
            0,
            256
        ]
    },
    "15": {
        "target_rect": [
            0,
            234
        ]
    },
    "16": {
        "obstacle_rect": [
            [
                25,
                192,
                "moving",
                3
            ]
        ],
        "target_rect": [
            0,
            206
        ]
    },
    "17": {
        "obstacle_rect": [
            [
                25,
                231,
                "ghost",
                0
            ]
        ],
        "target_rect": [
            0,
            272
        ]
    },
    "18": {
        "obstacle_rect": [
            [
                25,
                229,
                "switch",
                0
            ]
        ],
        "target_rect": [
            0,
            173
        ]
    },
    "19": {
        "obstacle_rect": [
            [
                25,
                162,
                "switch",
                0
            ]
        ],
        "target_rect": [
            0,
            198
        ]
    },
    "20": {
        "obstacle_rect": [
            [
                25,
                301,
                "moving",
                2
            ]
        ],
        "target_rect": [
            0,
            284
        ]
    },
    "21": {
        "obstacle_rect": [
            [
                25,
                168,
                "switch",
                0
            ]
        ],
        "target_rect": [
            0,
            198
        ]
    },
    "22": {
        "obstacle_rect": [
            [
                25,
                200,
                "ghost",
                0
            ]
        ],
        "target_rect": [
            0,
            269
        ]
    },
    "23": {
        "obstacle_rect": [
            [
                25,
                253,
                "switch",
                0
            ]
        ],
        "target_rect": [
            0,
            326
        ]
    },
    "24": {
        "obstacle_rect": [
            [
                25,
                261,
                "ghost",
                0
            ]
        ],
        "target_rect": [
            0,
            214
        ]
    },
    "25": {
        "obstacle_rect": [
            [
                25,
                329,
                "moving",
                -1
            ]
        ],
        "target_rect": [
            0,
            280
        ]
    },
    "26": {
        "obstacle_rect": [
            [
                25,
                285,
                "moving",
                -3
            ]
        ],
        "target_rect": [
            0,
            162
        ]
    },
    "27": {
        "obstacle_rect": [
            [
                25,
                243,
                "switch",
                0
            ]
        ],
        "target_rect": [
            0,
            227
        ]
    },
    "28": {
        "obstacle_rect": [
            [
                25,
                164,
                "ghost",
                0
            ]
        ],
        "target_rect": [
            0,
            163
        ]
    },
    "29": {
        "obstacle_rect": [
            [
                25,
                188,
                "moving",
                -3
            ],
            [
                25,
                317,
                "moving",
                1
            ]
        ],
        "target_rect": [
            0,
            208
        ]
    },
    "30": {
        "obstacle_rect": [
            [
                25,
                228,
                "ghost",
                0
            ],
            [
                25,
                285,
                "moving",
                3
            ]
        ],
        "target_rect": [
            0,
            156
        ]
    },
    "31": {
        "obstacle_rect": [
            [
                25,
                168,
                "ghost",
                0
            ],
            [
                25,
                271,
                "switch",
                0
            ]
        ],
        "target_rect": [
            0,
            233
        ]
    },
    "32": {
        "obstacle_rect": [
            [
                25,
                211,
                "ghost",
                0
            ],
            [
                25,
                294,
                "moving",
                -2
            ]
        ],
        "target_rect": [
            0,
            170
        ]
    },
    "33": {
        "obstacle_rect": [
            [
                25,
                245,
                "switch",
                0
            ],
            [
                25,
                190,
                "switch",
                0
            ]
        ],
        "target_rect": [
            0,
            172
        ]
    },
    "34": {
        "obstacle_rect": [
            [
                25,
                235,
                "switch",
                0
            ],
            [
                25,
                164,
                "switch",
                0
            ]
        ],
        "target_rect": [
            0,
            164
        ]
    },
    "35": {
        "obstacle_rect": [
            [
                25,
                152,
                "switch",
                0
            ],
            [
                25,
                254,
                "switch",
                0
            ]
        ],
        "target_rect": [
            0,
            199
        ]
    },
    "36": {
        "obstacle_rect": [
            [
                25,
                272,
                "moving",
                -1
            ],
            [
                25,
                183,
                "moving",
                1
            ]
        ],
        "target_rect": [
            0,
            296
        ]
    },
    "37": {
        "obstacle_rect": [
            [
                25,
                253,
                "moving",
                -2
            ],
            [
                25,
                184,
                "switch",
                0
            ]
        ],
        "target_rect": [
            0,
            313
        ]
    },
    "38": {
        "obstacle_rect": [
            [
                25,
                212,
                "switch",
                0
            ],
            [
                25,
                331,
                "bouncy",
                1
            ]
        ],
        "target_rect": [
            0,
            192
        ]
    },
    "39": {
        "obstacle_rect": [
            [
                25,
                282,
                "ghost",
                0
            ],
            [
                25,
                192,
                "switch",
                0
            ]
        ],
        "target_rect": [
            0,
            320
        ]
    },
    "40": {
        "obstacle_rect": [
            [
                25,
                215,
                "switch",
                0
            ],
            [
                25,
                309,
                "moving",
                3
            ]
        ],
        "target_rect": [
            0,
            323
        ]
    },
    "41": {
        "obstacle_rect": [
            [
                25,
                172,
                "moving",
                -3
            ],
            [
                25,
                304,
                "moving",
                3
            ]
        ],
        "target_rect": [
            0,
            208
        ]
    },
    "42": {
        "obstacle_rect": [
            [
                25,
                272,
                "moving",
                3
            ],
            [
                25,
                196,
                "moving",
                1
            ]
        ],
        "target_rect": [
            0,
            236
        ]
    },
    "43": {
        "obstacle_rect": [
            [
                25,
                157,
                "moving",
                3
            ],
            [
                25,
                258,
                "bouncy",
                -2
            ]
        ],
        "target_rect": [
            0,
            322
        ]
    },
    "44": {
        "obstacle_rect": [
            [
                25,
                246,
                "switch",
                0
            ],
            [
                25,
                303,
                "moving",
                2
            ]
        ],
        "target_rect": [
            0,
            292
        ]
    },
    "45": {
        "obstacle_rect": [
            [
                25,
                319,
                "ghost",
                0
            ],
            [
                25,
                227,
                "switch",
                0
            ]
        ],
        "target_rect": [
            0,
            156
        ]
    },
    "46": {
        "obstacle_rect": [
            [
                25,
                265,
                "ghost",
                0
            ],
            [
                25,
                163,
                "bouncy",
                -1
            ]
        ],
        "target_rect": [
            0,
            237
        ]
    },
    "47": {
        "obstacle_rect": [
            [
                25,
                237,
                "switch",
                0
            ],
            [
                25,
                326,
                "moving",
                -2
            ]
        ],
        "target_rect": [
            0,
            323
        ]
    },
    "48": {
        "obstacle_rect": [
            [
                25,
                311,
                "ghost",
                0
            ],
            [
                25,
                217,
                "moving",
                3
            ]
        ],
        "target_rect": [
            0,
            255
        ]
    },
    "49": {
        "obstacle_rect": [
            [
                25,
                219,
                "ghost",
                0
            ],
            [
                25,
                338,
                "moving",
                3
            ]
        ],
        "target_rect": [
            0,
            203
        ]
    },
    "50": {
        "obstacle_rect": [
            [
                25,
                183,
                "switch",
                0
            ],
            [
                25,
                268,
                "moving",
                -3
            ]
        ],
        "target_rect": [
            0,
            273
        ]
    },
    "51": {
        "obstacle_rect": [
            [
                25,
                314,
                "ghost",
                0
            ],
            [
                25,
                155,
                "switch",
                0
            ],
            [
                25,
                216,
                "moving",
                3
            ]
        ],
        "target_rect": [
            0,
            319
        ]
    },
    "52": {
        "obstacle_rect": [
            [
                25,
                244,
                "moving",
                -1
            ],
            [
                25,
                325,
                "switch",
                0
            ],
            [
                25,
                182,
                "switch",
                0
            ]
        ],
        "target_rect": [
            0,
            286
        ]
    },
    "53": {
        "obstacle_rect": [
            [
                25,
                227,
                "moving",
                2
            ],
            [
                25,
                293,
                "bouncy",
                -2
            ],
            [
                25,
                166,
                "switch",
                0
            ]
        ],
        "target_rect": [
            0,
            194
        ]
    },
    "54": {
        "obstacle_rect": [
            [
                25,
                163,
                "switch",
                0
            ],
            [
                25,
                292,
                "switch",
                0
            ],
            [
                25,
                229,
                "bouncy",
                -1
            ]
        ],
        "target_rect": [
            0,
            259
        ]
    },
    "55": {
        "obstacle_rect": [
            [
                25,
                277,
                "moving",
                -3
            ],
            [
                25,
                187,
                "switch",
                0
            ],
            [
                25,
                339,
                "moving",
                2
            ]
        ],
        "target_rect": [
            0,
            321
        ]
    },
    "56": {
        "obstacle_rect": [
            [
                25,
                218,
                "switch",
                0
            ],
            [
                25,
                299,
                "bouncy",
                -3
            ],
            [
                25,
                164,
                "switch",
                0
            ]
        ],
        "target_rect": [
            0,
            216
        ]
    },
    "57": {
        "obstacle_rect": [
            [
                25,
                228,
                "moving",
                -3
            ],
            [
                25,
                151,
                "moving",
                -2
            ],
            [
                25,
                325,
                "bouncy",
                -3
            ]
        ],
        "target_rect": [
            0,
            258
        ]
    },
    "58": {
        "obstacle_rect": [
            [
                25,
                255,
                "ghost",
                0
            ],
            [
                25,
                331,
                "moving",
                -1
            ],
            [
                25,
                158,
                "switch",
                0
            ]
        ],
        "target_rect": [
            0,
            159
        ]
    },
    "59": {
        "obstacle_rect": [
            [
                25,
                223,
                "ghost",
                0
            ],
            [
                25,
                298,
                "moving",
                -3
            ],
            [
                25,
                154,
                "bouncy",
                2
            ]
        ],
        "target_rect": [
            0,
            268
        ]
    },
    "60": {
        "obstacle_rect": [
            [
                25,
                195,
                "moving",
                3
            ],
            [
                25,
                332,
                "moving",
                1
            ],
            [
                25,
                275,
                "moving",
                -1
            ]
        ],
        "target_rect": [
            0,
            306
        ]
    },
    "61": {
        "obstacle_rect": [
            [
                25,
                222,
                "ghost",
                0
            ],
            [
                25,
                334,
                "moving",
                -2
            ],
            [
                25,
                157,
                "switch",
                0
            ]
        ],
        "target_rect": [
            0,
            182
        ]
    },
    "62": {
        "obstacle_rect": [
            [
                25,
                223,
                "ghost",
                0
            ],
            [
                25,
                311,
                "switch",
                0
            ],
            [
                25,
                158,
                "bouncy",
                -1
            ]
        ],
        "target_rect": [
            0,
            245
        ]
    },
    "63": {
        "obstacle_rect": [
            [
                25,
                264,
                "ghost",
                0
            ],
            [
                25,
                161,
                "switch",
                0
            ],
            [
                25,
                316,
                "switch",
                0
            ]
        ],
        "target_rect": [
            0,
            332
        ]
    },
    "64": {
        "obstacle_rect": [
            [
                25,
                327,
                "switch",
                0
            ],
            [
                25,
                239,
                "moving",
                2
            ],
            [
                25,
                155,
                "bouncy",
                1
            ]
        ],
        "target_rect": [
            0,
            312
        ]
    },
    "65": {
        "obstacle_rect": [
            [
                25,
                260,
                "moving",
                -1
            ],
            [
                25,
                330,
                "switch",
                0
            ],
            [
                25,
                167,
                "switch",
                0
            ]
        ],
        "target_rect": [
            0,
            260
        ]
    },
    "66": {
        "obstacle_rect": [
            [
                25,
                225,
                "switch",
                0
            ],
            [
                25,
                166,
                "bouncy",
                2
            ],
            [
                25,
                292,
                "switch",
                0
            ]
        ],
        "target_rect": [
            0,
            182
        ]
    },
    "67": {
        "obstacle_rect": [
            [
                25,
                170,
                "switch",
                0
            ],
            [
                25,
                311,
                "moving",
                -2
            ],
            [
                25,
                230,
                "bouncy",
                -1
            ]
        ],
        "target_rect": [
            0,
            185
        ]
    },
    "68": {
        "obstacle_rect": [
            [
                25,
                252,
                "switch",
                0
            ],
            [
                25,
                311,
                "moving",
                -2
            ],
            [
                25,
                184,
                "bouncy",
                3
            ]
        ],
        "target_rect": [
            0,
            243
        ]
    },
    "69": {
        "obstacle_rect": [
            [
                25,
                243,
                "switch",
                0
            ],
            [
                25,
                327,
                "bouncy",
                -2
            ],
            [
                25,
                178,
                "moving",
                1
            ]
        ],
        "target_rect": [
            0,
            249
        ]
    },
    "70": {
        "obstacle_rect": [
            [
                25,
                253,
                "moving",
                1
            ],
            [
                25,
                325,
                "switch",
                0
            ],
            [
                25,
                150,
                "moving",
                2
            ]
        ],
        "target_rect": [
            0,
            270
        ]
    },
    "71": {
        "obstacle_rect": [
            [
                25,
                310,
                "ghost",
                0
            ],
            [
                25,
                238,
                "switch",
                0
            ],
            [
                25,
                175,
                "switch",
                0
            ]
        ],
        "target_rect": [
            0,
            310
        ]
    },
    "72": {
        "obstacle_rect": [
            [
                25,
                154,
                "switch",
                0
            ],
            [
                25,
                245,
                "switch",
                0
            ],
            [
                25,
                303,
                "moving",
                3
            ]
        ],
        "target_rect": [
            0,
            329
        ]
    },
    "73": {
        "obstacle_rect": [
            [
                25,
                238,
                "moving",
                -3
            ],
            [
                25,
                331,
                "moving",
                2
            ],
            [
                25,
                184,
                "moving",
                1
            ]
        ],
        "target_rect": [
            0,
            295
        ]
    },
    "74": {
        "obstacle_rect": [
            [
                25,
                203,
                "switch",
                0
            ],
            [
                25,
                271,
                "bouncy",
                3
            ],
            [
                25,
                339,
                "switch",
                0
            ]
        ],
        "target_rect": [
            0,
            253
        ]
    },
    "75": {
        "obstacle_rect": [
            [
                25,
                257,
                "ghost",
                0
            ],
            [
                25,
                159,
                "switch",
                0
            ],
            [
                25,
                333,
                "moving",
                1
            ]
        ],
        "target_rect": [
            0,
            319
        ]
    }
}